func3lib/__init__.py
func3lib/func3lt.py
func3lib/README.md
func3lib-0.0.9.dist-info/LICENSE.txt
func3lib-0.0.9.dist-info/METADATA
func3lib-0.0.9.dist-info/WHEEL
func3lib-0.0.9.dist-info/RECORD
