Metadata-Version: 2.1
Name: func3lib
Version: 0.0.9
Summary: Three functions func3lib: 'transpose2d', 'window1d' and 'convolution2d'.
License: MIT
Author: LinasTamk
Author-email: linastamk@gmail.com
Requires-Python: >=3.10
Classifier: License :: OSI Approved :: MIT License
Classifier: Programming Language :: Python :: 3
Classifier: Programming Language :: Python :: 3.10
Classifier: Programming Language :: Python :: 3.11
Classifier: Programming Language :: Python :: 3.12
Requires-Dist: numpy (>=1.26.2,<2.0.0)
